nicegui_scanner/__init__.py
nicegui_scanner/barcode_scanner.vue
nicegui_scanner/scanner.py
nicegui_scanner/static/.gitkeep
nicegui_scanner/static/zxing.min.js
nicegui_scanner-0.4.0.dist-info/METADATA
nicegui_scanner-0.4.0.dist-info/WHEEL
nicegui_scanner-0.4.0.dist-info/licenses/LICENSE
nicegui_scanner-0.4.0.dist-info/RECORD
