Metadata-Version: 2.4
Name: nicegui-scanner
Version: 0.4.0
Summary: A barcode scanner component for NiceGUI applications
Project-URL: Homepage, https://github.com/serraict/nicegui-scanner-app
Project-URL: Repository, https://github.com/serraict/nicegui-scanner-app
Project-URL: Issues, https://github.com/serraict/nicegui-scanner-app/issues
Author: NiceGUI Scanner Contributors
License: MIT
License-File: LICENSE
Keywords: barcode,camera,nicegui,qr-code,scanner,vue
Classifier: Development Status :: 4 - Beta
Classifier: Intended Audience :: Developers
Classifier: License :: OSI Approved :: MIT License
Classifier: Programming Language :: Python :: 3
Classifier: Programming Language :: Python :: 3.8
Classifier: Programming Language :: Python :: 3.9
Classifier: Programming Language :: Python :: 3.10
Classifier: Programming Language :: Python :: 3.11
Classifier: Programming Language :: Python :: 3.12
Classifier: Topic :: Multimedia :: Graphics :: Capture :: Digital Camera
Classifier: Topic :: Software Development :: Libraries :: Python Modules
Requires-Python: >=3.8
Requires-Dist: nicegui>=1.0.0
